hello.py
metatorch-0.0.1.dist-info/METADATA
metatorch-0.0.1.dist-info/WHEEL
metatorch-0.0.1.dist-info/top_level.txt
metatorch-0.0.1.dist-info/RECORD
